ConCnnet/__init__.py
ConCnnet/network.cpython-311-darwin.so
ConCnnet-0.1.0.dist-info/LICENSE.txt
ConCnnet-0.1.0.dist-info/METADATA
ConCnnet-0.1.0.dist-info/WHEEL
ConCnnet-0.1.0.dist-info/top_level.txt
ConCnnet-0.1.0.dist-info/RECORD
